storage_service/__init__.py
storage_service/storage.py
storage_service-0.0.2.dist-info/LICENSE
storage_service-0.0.2.dist-info/METADATA
storage_service-0.0.2.dist-info/WHEEL
storage_service-0.0.2.dist-info/top_level.txt
storage_service-0.0.2.dist-info/RECORD
