Metadata-Version: 2.1
Name: storage-service
Version: 0.0.2
Summary: Storage Service is a Django + DRF package that help to work with model.
Home-page: https://github.com/ebs-integrator/storage-service
Author: Victor Elceaninov & Dorin Musteata
Author-email: victor.elceaninov@ebs-integrator.org, dorin.musteata@ebs-integrator.org
License: UNKNOWN
Project-URL: Bug Tracker, https://github.com/ebs-integrator/storage-service/issues
Platform: UNKNOWN
Classifier: Programming Language :: Python :: 3
Classifier: Programming Language :: Python :: 3.6
Classifier: Programming Language :: Python :: 3.7
Classifier: Programming Language :: Python :: 3.8
Classifier: Programming Language :: Python :: 3.9
Classifier: License :: OSI Approved :: MIT License
Classifier: Operating System :: OS Independent
Requires-Python: >=3.6
